{"filename":"-100.75-23.75","collections":[{"name":"restaurants","data":[{"_id":"5c3d65bd3525a329e0c0dda4","address":"Calle Morelos 709","location":{"type":"Point","coordinates":[-100.642497,23.643826]},"isApproved":true,"items":[],"keys":["Seafood"],"lastUpdated":1547527612563,"name":"Mariscos Santa Fe","phone":"48 888 20753","price":"","reviewCount":1,"reviewScore":3,"meta":{"revision":0,"created":1547531153278,"version":0},"$loki":1},{"_id":"5c3d65bd3525a329e0c054df","address":"Carr. 57 S/N","location":{"type":"Point","coordinates":[-100.635485503328,23.6631258489739]},"isApproved":true,"items":[],"keys":["Mexican"],"lastUpdated":1547527612347,"name":"El Mezquite","phone":"","price":"","reviewCount":1,"reviewScore":5,"meta":{"revision":0,"created":1547531153278,"version":0},"$loki":2},{"_id":"5c3d65bd3525a329e0bffd18","address":"Uruguay 102","location":{"type":"Point","coordinates":[-100.63632082352,23.6617980466733]},"isApproved":true,"items":[],"keys":["Mexican"],"lastUpdated":1547527612222,"name":"La Noria","phone":"48 888 25334","price":"","reviewCount":3,"reviewScore":4,"meta":{"revision":0,"created":1547531153278,"version":0},"$loki":3},{"_id":"5c3d65bd3525a329e0c133e8","address":"Matehuala-Saltillo","location":{"type":"Point","coordinates":[-100.628978542451,23.6759017420484]},"isApproved":true,"items":[],"keys":["Tacos"],"lastUpdated":1547527612690,"name":"Tacos Y Tortas el Rey","phone":"","price":"$","reviewCount":1,"reviewScore":3,"meta":{"revision":0,"created":1547531153278,"version":0},"$loki":4},{"_id":"5c3d65bd3525a329e0c00ece","address":"Lanzagorta 27","location":{"type":"Point","coordinates":[-100.886943,23.68993]},"isApproved":true,"items":[],"keys":["Cafeteria"],"lastUpdated":1547527612237,"name":"El Café Azul","phone":"48 888 75131","price":"","reviewCount":0,"reviewScore":0,"meta":{"revision":0,"created":1547531153278,"version":0},"$loki":5},{"_id":"5c3d65bd3525a329e0c0a359","address":"Lanzagorta s/n","location":{"type":"Point","coordinates":[-100.885450579226,23.6897947166682]},"isApproved":true,"items":[],"keys":["Mexican"],"lastUpdated":1547527612474,"name":"Las Gorditas de Chila","phone":"","price":"","reviewCount":1,"reviewScore":3,"meta":{"revision":0,"created":1547531153278,"version":0},"$loki":6},{"_id":"5c3d65bd3525a329e0c0f4f6","address":"","location":{"type":"Point","coordinates":[-100.886801406741,23.6903682358792]},"isApproved":true,"items":[],"keys":["Salad","Pizza","Mexican"],"lastUpdated":1547527612592,"name":"mesón de la abundancia","phone":"","price":"","reviewCount":1,"reviewScore":5,"meta":{"revision":0,"created":1547531153278,"version":0},"$loki":7}],"idIndex":[1,2,3,4,5,6,7],"binaryIndices":{},"constraints":null,"uniqueNames":[],"transforms":{},"objType":"restaurants","dirty":true,"cachedIndex":null,"cachedBinaryIndex":null,"cachedData":null,"adaptiveBinaryIndices":true,"transactional":false,"cloneObjects":false,"cloneMethod":"parse-stringify","asyncListeners":false,"disableMeta":false,"disableChangesApi":true,"disableDeltaChangesApi":true,"autoupdate":false,"serializableIndices":true,"ttl":null,"maxId":7,"DynamicViews":[],"events":{"insert":[],"update":[],"pre-insert":[],"pre-update":[],"close":[],"flushbuffer":[],"error":[],"delete":[null],"warning":[null]},"changes":[]}],"databaseVersion":1.5,"engineVersion":1.5,"autosave":false,"autosaveInterval":5000,"autosaveHandle":null,"throttledSaves":true,"options":{"serializationMethod":"normal","destructureDelimiter":"$<\n"},"persistenceMethod":"fs","persistenceAdapter":null,"verbose":false,"events":{"init":[null],"loaded":[],"flushChanges":[],"close":[],"changes":[],"warning":[]},"ENV":"NODEJS"}