{"filename":"-112.75-37.5","collections":[{"name":"restaurants","data":[{"_id":"5c3d65bd3525a329e0c0d140","address":"84 N Main St","location":{"type":"Point","coordinates":[-112.8523985,37.7055604]},"isApproved":true,"items":[],"keys":["Chinese","Buffets"],"lastUpdated":1547527612545,"name":"Hong Kong Buffet","phone":"(435) 865-8986","price":"$$","reviewCount":72,"reviewScore":3.5,"meta":{"revision":0,"created":1547531155335,"version":0},"$loki":1},{"_id":"5c3d65bd3525a329e0c0b45b","address":"281 Zion Park Blvd","location":{"type":"Point","coordinates":[-112.849882096052,37.7051991010293]},"isApproved":true,"items":[],"keys":["Bars","Burgers","Pizza"],"lastUpdated":1547527612499,"name":"Bistro H","phone":"(435) 216-1639","price":"$$","reviewCount":20,"reviewScore":3.5,"meta":{"revision":0,"created":1547531155335,"version":0},"$loki":2},{"_id":"5c3d65bd3525a329e0c15955","address":"1102 W 200th N","location":{"type":"Point","coordinates":[-112.849978,37.7021135]},"isApproved":true,"items":[],"keys":["Fast Food","Ice Cream & Frozen Yogurt"],"lastUpdated":1547527612747,"name":"Dairy Queen","phone":"(435) 233-2037","price":"","reviewCount":2,"reviewScore":5,"meta":{"revision":0,"created":1547531155335,"version":0},"$loki":3},{"_id":"5c3d65bd3525a329e0c1665e","address":"1149 Zion Park Blvd","location":{"type":"Point","coordinates":[-113.0616517,37.6923742]},"isApproved":true,"items":[],"keys":["Bars","American (New)"],"lastUpdated":1547527612765,"name":"Jacks Sports Grill","phone":"(435) 772-3700","price":"$$","reviewCount":182,"reviewScore":3.5,"meta":{"revision":0,"created":1547531155335,"version":0},"$loki":4},{"_id":"5c3d65bd3525a329e0c0d981","address":"1872 W Cross Hollow Rd","location":{"type":"Point","coordinates":[-113.062905889548,37.6938518991452]},"isApproved":true,"items":[],"keys":["Chinese","Fast Food"],"lastUpdated":1547527612555,"name":"Panda Express","phone":"(435) 586-5042","price":"$","reviewCount":22,"reviewScore":2.5,"meta":{"revision":0,"created":1547531155335,"version":0},"$loki":5},{"_id":"5c3d65bd3525a329e0c07de7","address":"535 West State Street","location":{"type":"Point","coordinates":[-113.0745886,37.6805708]},"isApproved":true,"items":[],"keys":["Pizza"],"lastUpdated":1547527612416,"name":"Papa Murphy’s","phone":"(435) 635-7272","price":"$$","reviewCount":7,"reviewScore":3.5,"meta":{"revision":0,"created":1547531155335,"version":0},"$loki":6},{"_id":"5c3d65bd3525a329e0c0e683","address":"1330 Providence Center Dr","location":{"type":"Point","coordinates":[-113.0745886,37.6805708]},"isApproved":true,"items":[],"keys":["Fast Food","Burgers","Coffee & Tea"],"lastUpdated":1547527612574,"name":"McDonald’s","phone":"(435) 865-7881","price":"","reviewCount":4,"reviewScore":2,"meta":{"revision":0,"created":1547531155335,"version":0},"$loki":7},{"_id":"5c3d65bd3525a329e0c16c62","address":"820 S Main St","location":{"type":"Point","coordinates":[-113.075403,37.6805014]},"isApproved":true,"items":[],"keys":["Mexican"],"lastUpdated":1547527612774,"name":"Taco Time","phone":"(435) 586-3614","price":"","reviewCount":6,"reviewScore":2,"meta":{"revision":0,"created":1547531155335,"version":0},"$loki":8},{"_id":"5c3d65bd3525a329e0c15c09","address":"1141 W State St","location":{"type":"Point","coordinates":[-113.07381804857,37.6810973662633]},"isApproved":true,"items":[],"keys":["Chinese"],"lastUpdated":1547527612754,"name":"Hunan City","phone":"(435) 635-6882","price":"$$","reviewCount":101,"reviewScore":3.5,"meta":{"revision":0,"created":1547531155335,"version":0},"$loki":9},{"_id":"5c3d65bd3525a329e0c09742","address":"476 E Midvalley Rd","location":{"type":"Point","coordinates":[-113.073517,37.680813]},"isApproved":true,"items":[],"keys":["Pizza","Grocery"],"lastUpdated":1547527612461,"name":"The Hub - Pizza and More","phone":"(435) 865-6623","price":"$","reviewCount":12,"reviewScore":4,"meta":{"revision":0,"created":1547531155335,"version":0},"$loki":10},{"_id":"5c3d65bd3525a329e0c18669","address":"579 S Main St","location":{"type":"Point","coordinates":[-113.076481,37.681241]},"isApproved":true,"items":[],"keys":["Pizza","Italian","Chicken Wings"],"lastUpdated":1547527612815,"name":"Pizza Hut","phone":"(435) 586-9896","price":"$$","reviewCount":29,"reviewScore":2,"meta":{"revision":0,"created":1547531155335,"version":0},"$loki":11},{"_id":"5c3d65bd3525a329e0c0dc36","address":"1030 N 2600th W","location":{"type":"Point","coordinates":[-113.0769154,37.6811938]},"isApproved":true,"items":[],"keys":["American (New)","Breakfast & Brunch"],"lastUpdated":1547527612556,"name":"Sky Mountain Grill","phone":"(435) 635-7888","price":"","reviewCount":9,"reviewScore":4.5,"meta":{"revision":0,"created":1547531155335,"version":0},"$loki":12},{"_id":"5c3d65bd3525a329e0c18aca","address":"775 West 200 North","location":{"type":"Point","coordinates":[-113.0775792,37.6821679]},"isApproved":true,"items":[],"keys":["Mexican","Tex-Mex","Fast Food"],"lastUpdated":1547527612823,"name":"Taco Bell","phone":"(435) 586-4445","price":"$","reviewCount":19,"reviewScore":4.5,"meta":{"revision":0,"created":1547531155335,"version":0},"$loki":13},{"_id":"5c3d65bd3525a329e0c0b236","address":"3785 Movie Ranch Rd","location":{"type":"Point","coordinates":[-113.0777297,37.6815181]},"isApproved":true,"items":[],"keys":["Pizza","Mexican","Sandwiches"],"lastUpdated":1547527612498,"name":"Mark’s Sub Shop","phone":"(435) 682-3513","price":"$","reviewCount":2,"reviewScore":4.5,"meta":{"revision":0,"created":1547531155335,"version":0},"$loki":14},{"_id":"5c3d65bd3525a329e0c08080","address":"805 Zion Park Blvd","location":{"type":"Point","coordinates":[-113.077295199037,37.6803791010568]},"isApproved":true,"items":[],"keys":["Mexican"],"lastUpdated":1547527612419,"name":"Casa de Amigos","phone":"(435) 772-0422","price":"$$","reviewCount":317,"reviewScore":3.5,"meta":{"revision":0,"created":1547531155335,"version":0},"$loki":15},{"_id":"5c3d65bd3525a329e0c1ab07","address":"222 W State St","location":{"type":"Point","coordinates":[-113.076392,37.680596]},"isApproved":true,"items":[],"keys":["Buffets","Chinese","Sushi Bars"],"lastUpdated":1547527612868,"name":"China Buffet","phone":"(435) 635-5563","price":"$","reviewCount":97,"reviewScore":3.5,"meta":{"revision":0,"created":1547531155335,"version":0},"$loki":16},{"_id":"5c3d65bd3525a329e0c0ad14","address":"1585 W Ledges Pkwy","location":{"type":"Point","coordinates":[-113.0816387,37.6803973]},"isApproved":true,"items":[],"keys":["Seafood","American (Traditional)","Steakhouses"],"lastUpdated":1547527612490,"name":"The Fish Rock Grille","phone":"(435) 634-4650","price":"$$","reviewCount":18,"reviewScore":3,"meta":{"revision":0,"created":1547531155335,"version":0},"$loki":17},{"_id":"5c3d65bd3525a329e0c19bcd","address":"1840 N Main St","location":{"type":"Point","coordinates":[-113.0791491,37.6804696]},"isApproved":true,"items":[],"keys":["Burgers","Fast Food"],"lastUpdated":1547527612850,"name":"Arctic Circle","phone":"(435) 867-5716","price":"$","reviewCount":2,"reviewScore":3,"meta":{"revision":0,"created":1547531155335,"version":0},"$loki":18},{"_id":"5c3d65bd3525a329e0c0aea0","address":"E Hwy 9 Zion National Park Ut 84767","location":{"type":"Point","coordinates":[-113.062338,37.6817624]},"isApproved":true,"items":[],"keys":["American (New)"],"lastUpdated":1547527612491,"name":"Cordwood","phone":"(866) 648-2555","price":"$$$$","reviewCount":23,"reviewScore":3,"meta":{"revision":0,"created":1547531155335,"version":0},"$loki":19},{"_id":"5c3d65bd3525a329e0c15927","address":"1000 W Hwy 9","location":{"type":"Point","coordinates":[-113.062338,37.6817624]},"isApproved":true,"items":[],"keys":["American (Traditional)","Barbeque"],"lastUpdated":1547527612747,"name":"Fort Zion","phone":"(435) 635-3455","price":"$$","reviewCount":94,"reviewScore":4,"meta":{"revision":0,"created":1547531155335,"version":0},"$loki":20},{"_id":"5c3d65bd3525a329e0c03f4a","address":"30 N Main St","location":{"type":"Point","coordinates":[-113.061382356913,37.6824662795416]},"isApproved":true,"items":[],"keys":["American (Traditional)","Mexican"],"lastUpdated":1547527612319,"name":"Calvario’s Family Restaurant","phone":"(435) 477-9069","price":"$","reviewCount":40,"reviewScore":4.5,"meta":{"revision":0,"created":1547531155335,"version":0},"$loki":21},{"_id":"5c3d65bd3525a329e0c11fc0","address":"750 State St","location":{"type":"Point","coordinates":[-113.061382356913,37.6824662795416]},"isApproved":true,"items":[],"keys":["Food Trucks","Tacos"],"lastUpdated":1547527612662,"name":"LL Wagon Taco","phone":"(435) 799-6827","price":"$","reviewCount":26,"reviewScore":4.5,"meta":{"revision":0,"created":1547531155335,"version":0},"$loki":22},{"_id":"5c3d65bd3525a329e0c1a882","address":"379 W State St","location":{"type":"Point","coordinates":[-113.0606279,37.6805332]},"isApproved":true,"items":[],"keys":["Mexican"],"lastUpdated":1547527612867,"name":"Taco Bell","phone":"(435) 635-5676","price":"$","reviewCount":14,"reviewScore":2,"meta":{"revision":0,"created":1547531155335,"version":0},"$loki":23},{"_id":"5c3d65bd3525a329e0c0bbd3","address":"2645 N Canyon Ranch Dr","location":{"type":"Point","coordinates":[-113.0606689,37.6791455]},"isApproved":true,"items":[],"keys":["Sandwiches","Fast Food"],"lastUpdated":1547527612509,"name":"Subway","phone":"(435) 867-9963","price":"$","reviewCount":8,"reviewScore":2.5,"meta":{"revision":0,"created":1547531155335,"version":0},"$loki":24},{"_id":"5c3d65bd3525a329e0c10ea4","address":"777 S Main St","location":{"type":"Point","coordinates":[-113.0614423,37.6752658]},"isApproved":true,"items":[],"keys":["Fast Food","Ice Cream & Frozen Yogurt"],"lastUpdated":1547527612634,"name":"Dairy Queen","phone":"(435) 865-1262","price":"$","reviewCount":20,"reviewScore":3.5,"meta":{"revision":0,"created":1547531155335,"version":0},"$loki":25},{"_id":"5c3d65bd3525a329e0c147d7","address":"259 Village Way","location":{"type":"Point","coordinates":[-113.061785660684,37.6757709148741]},"isApproved":true,"items":[],"keys":["Thai"],"lastUpdated":1547527612721,"name":"Sook Jai Thai Cuisine","phone":"(435) 990-1491","price":"$$","reviewCount":80,"reviewScore":4.5,"meta":{"revision":0,"created":1547531155335,"version":0},"$loki":26},{"_id":"5c3d65bd3525a329e0c113ad","address":"1100 Tuacahn Dr","location":{"type":"Point","coordinates":[-113.0618931,37.6774769]},"isApproved":true,"items":[],"keys":["Greek","Food Trucks","Barbeque"],"lastUpdated":1547527612642,"name":"Chef Hog","phone":"(435) 652-3352","price":"$","reviewCount":30,"reviewScore":4.5,"meta":{"revision":0,"created":1547531155335,"version":0},"$loki":27},{"_id":"5c3d65bd3525a329e0c14ede","address":"1212 Zion Park Blvd","location":{"type":"Point","coordinates":[-113.062026,37.677571]},"isApproved":true,"items":[],"keys":["Tex-Mex"],"lastUpdated":1547527612736,"name":"Bit & Spur Restaurant & Saloon","phone":"(435) 772-3498","price":"$$","reviewCount":526,"reviewScore":4,"meta":{"revision":0,"created":1547531155335,"version":0},"$loki":28},{"_id":"5c3d65bd3525a329e0c01715","address":"815 Coyote Gulch Ct","location":{"type":"Point","coordinates":[-113.062024,37.677575]},"isApproved":true,"items":[],"keys":["Coffee & Tea","American (New)","Vegetarian"],"lastUpdated":1547527612250,"name":"Xetava Gardens Cafe","phone":"(435) 656-0165","price":"$$","reviewCount":144,"reviewScore":4.5,"meta":{"revision":0,"created":1547531155335,"version":0},"$loki":29},{"_id":"5c3d65bd3525a329e0bff78f","address":"948 Zion Park Blvd","location":{"type":"Point","coordinates":[-113.0620174,37.6771167]},"isApproved":true,"items":[],"keys":["Mexican","Breakfast & Brunch"],"lastUpdated":1547527612218,"name":"Oscar’s Cafe","phone":"(435) 772-3232","price":"$$","reviewCount":1422,"reviewScore":4,"meta":{"revision":0,"created":1547531155335,"version":0},"$loki":30},{"_id":"5c3d65bd3525a329e0c00949","address":"1485 W 200th N","location":{"type":"Point","coordinates":[-113.062758,37.67757]},"isApproved":true,"items":[],"keys":["Sandwiches","Fast Food"],"lastUpdated":1547527612229,"name":"Subway","phone":"(435) 586-4981","price":"$","reviewCount":4,"reviewScore":3,"meta":{"revision":0,"created":1547531155335,"version":0},"$loki":31},{"_id":"5c3d65bd3525a329e0c0cde4","address":"890 N Main St","location":{"type":"Point","coordinates":[-113.062758,37.67757]},"isApproved":true,"items":[],"keys":["Mexican","Tex-Mex","Seafood"],"lastUpdated":1547527612534,"name":"La Botana at La Fiesta","phone":"(435) 586-2570","price":"$","reviewCount":23,"reviewScore":3.5,"meta":{"revision":0,"created":1547531155335,"version":0},"$loki":32},{"_id":"5c3d65bd3525a329e0c116e7","address":"5 N Main St","location":{"type":"Point","coordinates":[-113.062758,37.67757]},"isApproved":true,"items":[],"keys":["Mexican"],"lastUpdated":1547527612650,"name":"Alicia’s Tamales","phone":"","price":"","reviewCount":3,"reviewScore":3.5,"meta":{"revision":0,"created":1547531155335,"version":0},"$loki":33},{"_id":"5c3d65bd3525a329e0c16dd1","address":"95 Zion Park Blvd","location":{"type":"Point","coordinates":[-113.062758,37.67757]},"isApproved":true,"items":[],"keys":["Burgers","Brewpubs"],"lastUpdated":1547527612780,"name":"Zion Canyon Brewpub","phone":"(435) 772-0336","price":"$$","reviewCount":449,"reviewScore":3.5,"meta":{"revision":0,"created":1547531155335,"version":0},"$loki":34},{"_id":"5c3d65bd3525a329e0c1a9ee","address":"240 S Main St","location":{"type":"Point","coordinates":[-113.062758,37.67757]},"isApproved":true,"items":[],"keys":["Burgers"],"lastUpdated":1547527612868,"name":"Linski’s Grill and Hotel","phone":"(435) 691-6407","price":"","reviewCount":13,"reviewScore":4.5,"meta":{"revision":0,"created":1547531155335,"version":0},"$loki":35},{"_id":"5c3d65bd3525a329e0c03265","address":"1180 W State St","location":{"type":"Point","coordinates":[-113.0630012,37.6775625]},"isApproved":true,"items":[],"keys":["Fast Food","Burgers","Coffee & Tea"],"lastUpdated":1547527612296,"name":"McDonald’s","phone":"(435) 635-3188","price":"$","reviewCount":39,"reviewScore":2,"meta":{"revision":0,"created":1547531155335,"version":0},"$loki":36},{"_id":"5c3d65bd3525a329e0c11ca6","address":"33 N Main St","location":{"type":"Point","coordinates":[-113.0630594,37.6775906]},"isApproved":true,"items":[],"keys":["Cafes"],"lastUpdated":1547527612660,"name":"Parowan Cafe","phone":"(435) 477-3593","price":"$","reviewCount":87,"reviewScore":4,"meta":{"revision":0,"created":1547531155335,"version":0},"$loki":37},{"_id":"5c3d65bd3525a329e0c0fb11","address":"2275 E Hwy 14","location":{"type":"Point","coordinates":[-113.0615389,37.6785464]},"isApproved":true,"items":[],"keys":["Steakhouses","Barbeque","Seafood"],"lastUpdated":1547527612601,"name":"Rusty’s Ranch House","phone":"(435) 586-3839","price":"$$","reviewCount":57,"reviewScore":4,"meta":{"revision":0,"created":1547531155335,"version":0},"$loki":38},{"_id":"5c3d65bd3525a329e0c0b624","address":"259 S Village Way","location":{"type":"Point","coordinates":[-113.062176875875,37.6776463020327]},"isApproved":true,"items":[],"keys":["Pizza"],"lastUpdated":1547527612499,"name":"Pizanos Pizzeria","phone":"(435) 677-3341","price":"$$","reviewCount":142,"reviewScore":3,"meta":{"revision":0,"created":1547531155335,"version":0},"$loki":39},{"_id":"5c3d65bd3525a329e0c0bbdb","address":"70 E State St","location":{"type":"Point","coordinates":[-113.061216842789,37.6788442052239]},"isApproved":true,"items":[],"keys":["Mexican"],"lastUpdated":1547527612509,"name":"Lupita’s Mexican Food","phone":"(435) 635-0206","price":"$$","reviewCount":103,"reviewScore":3.5,"meta":{"revision":0,"created":1547531155335,"version":0},"$loki":40},{"_id":"5c3d65bd3525a329e0c09b4f","address":"1 Zion National Park","location":{"type":"Point","coordinates":[-113.061419,37.6789132]},"isApproved":true,"items":[],"keys":["Breakfast & Brunch","American (Traditional)"],"lastUpdated":1547527612464,"name":"Red Rock Grill","phone":"(435) 772-7760","price":"$$","reviewCount":109,"reviewScore":3,"meta":{"revision":0,"created":1547531155335,"version":0},"$loki":41},{"_id":"5c3d65bd3525a329e0c15af2","address":"86 W Center St","location":{"type":"Point","coordinates":[-113.061359314915,37.6792128900615]},"isApproved":true,"items":[],"keys":["Coffee & Tea","Sandwiches","Breakfast & Brunch"],"lastUpdated":1547527612753,"name":"The Pastry Pub","phone":"(435) 867-1400","price":"$","reviewCount":138,"reviewScore":4,"meta":{"revision":0,"created":1547531155335,"version":0},"$loki":42},{"_id":"5c3d65bd3525a329e0c0e5e6","address":"897 Zion Park Blvd","location":{"type":"Point","coordinates":[-113.0621636,37.68002]},"isApproved":true,"items":[],"keys":["Barbeque","Smokehouse","Breakfast & Brunch"],"lastUpdated":1547527612573,"name":"Porter’s Smokehouse and Grill","phone":"(435) 772-0115","price":"$$","reviewCount":111,"reviewScore":3.5,"meta":{"revision":0,"created":1547531155335,"version":0},"$loki":43},{"_id":"5c3d65bd3525a329e0c0b1c3","address":"501 S Main St","location":{"type":"Point","coordinates":[-113.0614888,37.6796274]},"isApproved":true,"items":[],"keys":["Diners","Breakfast & Brunch","American (Traditional)"],"lastUpdated":1547527612497,"name":"All American Diner","phone":"(435) 867-4211","price":"$","reviewCount":309,"reviewScore":4,"meta":{"revision":0,"created":1547531155335,"version":0},"$loki":44},{"_id":"5c3d65bd3525a329e0c10bb8","address":"709 Zion Park Blvd","location":{"type":"Point","coordinates":[-113.062366038407,37.6805937951467]},"isApproved":true,"items":[],"keys":["Breakfast & Brunch","American (New)"],"lastUpdated":1547527612632,"name":"Moki - Temp. CLOSED","phone":"(435) 215-0520","price":"$$","reviewCount":70,"reviewScore":4.5,"meta":{"revision":0,"created":1547531155335,"version":0},"$loki":45},{"_id":"5c3d65bd3525a329e0c07264","address":"982 W State St","location":{"type":"Point","coordinates":[-113.0629081,37.6787546]},"isApproved":true,"items":[],"keys":["Italian","Pizza"],"lastUpdated":1547527612398,"name":"Prospectors Place","phone":"(435) 773-0524","price":"$$","reviewCount":56,"reviewScore":3.5,"meta":{"revision":0,"created":1547531155335,"version":0},"$loki":46},{"_id":"5c3d65bd3525a329e0bfff21","address":"1149 Zion Park Blvd","location":{"type":"Point","coordinates":[-113.071855,37.6758]},"isApproved":true,"items":[],"keys":["Bars","Seafood","Steakhouses"],"lastUpdated":1547527612223,"name":"Switchback Grille","phone":"(435) 772-3700","price":"$$$","reviewCount":248,"reviewScore":3.5,"meta":{"revision":0,"created":1547531155335,"version":0},"$loki":47},{"_id":"5c3d65bd3525a329e0c061b2","address":"1149 W State St","location":{"type":"Point","coordinates":[-113.06819,37.6632031]},"isApproved":true,"items":[],"keys":["Burgers","Fast Food"],"lastUpdated":1547527612369,"name":"Wendy’s","phone":"(435) 635-6828","price":"$","reviewCount":10,"reviewScore":4,"meta":{"revision":0,"created":1547531155335,"version":0},"$loki":48},{"_id":"5c3d65bd3525a329e0c19103","address":"96 N Main St","location":{"type":"Point","coordinates":[-113.064374,37.6654464]},"isApproved":true,"items":[],"keys":["Pizza"],"lastUpdated":1547527612832,"name":"Little Caesars Pizza","phone":"(435) 586-1195","price":"$","reviewCount":5,"reviewScore":2,"meta":{"revision":0,"created":1547531155335,"version":0},"$loki":49},{"_id":"5c3d65bd3525a329e0c035df","address":"126 N Main St","location":{"type":"Point","coordinates":[-113.0663044,37.6639266]},"isApproved":true,"items":[],"keys":["Barbeque","American (Traditional)"],"lastUpdated":1547527612303,"name":"Charlie’s Southern Barbecue","phone":"(435) 867-8010","price":"$$","reviewCount":248,"reviewScore":4,"meta":{"revision":0,"created":1547531155335,"version":0},"$loki":50},{"_id":"5c3d65bd3525a329e0c0b9e0","address":"754 State St","location":{"type":"Point","coordinates":[-113.0664681,37.6637547]},"isApproved":true,"items":[],"keys":["Fast Food","Ice Cream & Frozen Yogurt"],"lastUpdated":1547527612507,"name":"Dairy Queen - Hurricane","phone":"(435) 635-5952","price":"$","reviewCount":34,"reviewScore":4,"meta":{"revision":0,"created":1547531155335,"version":0},"$loki":51},{"_id":"5c3d65bd3525a329e0c0a04c","address":"294 N Main St","location":{"type":"Point","coordinates":[-113.062117,37.6674768]},"isApproved":true,"items":[],"keys":["Sandwiches","Burgers","Ice Cream & Frozen Yogurt"],"lastUpdated":1547527612472,"name":"Hermie’s Drive-In","phone":"(435) 865-0612","price":"$","reviewCount":111,"reviewScore":4.5,"meta":{"revision":0,"created":1547531155335,"version":0},"$loki":52},{"_id":"5c3d65bd3525a329e0c17fac","address":"975 Zion Park Blvd","location":{"type":"Point","coordinates":[-113.0617422,37.6682954]},"isApproved":true,"items":[],"keys":["American (Traditional)","Creperies","Burgers"],"lastUpdated":1547527612802,"name":"MeMe’s Cafe","phone":"(435) 772-0114","price":"$$","reviewCount":829,"reviewScore":4.5,"meta":{"revision":0,"created":1547531155335,"version":0},"$loki":53},{"_id":"5c3d65bd3525a329e0c117d4","address":"667 S Main St","location":{"type":"Point","coordinates":[-113.0623264,37.6672068]},"isApproved":true,"items":[],"keys":["Fast Food","Sandwiches"],"lastUpdated":1547527612650,"name":"Subway","phone":"(435) 586-4338","price":"","reviewCount":3,"reviewScore":2.5,"meta":{"revision":0,"created":1547531155335,"version":0},"$loki":54},{"_id":"5c3d65bd3525a329e0c158c7","address":"895 West 200 N","location":{"type":"Point","coordinates":[-113.0615367,37.6692131]},"isApproved":true,"items":[],"keys":["Burgers","Fast Food","Hot Dogs"],"lastUpdated":1547527612747,"name":"A&W","phone":"(435) 586-3393","price":"","reviewCount":4,"reviewScore":2.5,"meta":{"revision":0,"created":1547531155335,"version":0},"$loki":55},{"_id":"5c3d65bd3525a329e0c160ce","address":"300 Main St","location":{"type":"Point","coordinates":[-113.0834325,37.6553483]},"isApproved":true,"items":[],"keys":["American (Traditional)"],"lastUpdated":1547527612757,"name":"Breaking Bread Bakery","phone":"","price":"","reviewCount":3,"reviewScore":3.5,"meta":{"revision":0,"created":1547531155335,"version":0},"$loki":56},{"_id":"5c3d65bd3525a329e0c02e04","address":"1313 S Providence Ctr Dr","location":{"type":"Point","coordinates":[-113.083721,37.655818]},"isApproved":true,"items":[],"keys":["Fast Food","Burgers"],"lastUpdated":1547527612294,"name":"Jack in the Box","phone":"(435) 586-7132","price":"$","reviewCount":13,"reviewScore":2.5,"meta":{"revision":0,"created":1547531155335,"version":0},"$loki":57},{"_id":"5c3d65bd3525a329e0c11f6e","address":"1141 W State St","location":{"type":"Point","coordinates":[-113.084347,37.65577]},"isApproved":true,"items":[],"keys":["Cafes","American (Traditional)"],"lastUpdated":1547527612662,"name":"Triple TJS Cafe","phone":"(435) 635-9014","price":"$$","reviewCount":63,"reviewScore":4,"meta":{"revision":0,"created":1547531155335,"version":0},"$loki":58},{"_id":"5c3d65bd3525a329e0c15e6e","address":"99 N State St","location":{"type":"Point","coordinates":[-113.083396889269,37.6564360225107]},"isApproved":true,"items":[],"keys":["Seafood","Steakhouses","Burgers"],"lastUpdated":1547527612755,"name":"Stage Coach Grille","phone":"(435) 635-7400","price":"$$","reviewCount":286,"reviewScore":4.5,"meta":{"revision":0,"created":1547531155335,"version":0},"$loki":59},{"_id":"5c3d65bd3525a329e0c0a83b","address":"1515 Zion Park Blvd","location":{"type":"Point","coordinates":[-113.083432,37.656364]},"isApproved":true,"items":[],"keys":["Bars","American (New)"],"lastUpdated":1547527612482,"name":"King’s Landing Bistro","phone":"(435) 772-7422","price":"$$","reviewCount":299,"reviewScore":4.5,"meta":{"revision":0,"created":1547531155335,"version":0},"$loki":60},{"_id":"5c3d65bd3525a329e0c106e3","address":"445 Zion Park Blvd","location":{"type":"Point","coordinates":[-113.083136,37.6563084992288]},"isApproved":true,"items":[],"keys":["Mexican","Asian Fusion","Burgers"],"lastUpdated":1547527612619,"name":"Whiptail Grill - Temp. CLOSED","phone":"(435) 772-0283","price":"$$","reviewCount":644,"reviewScore":4,"meta":{"revision":0,"created":1547531155335,"version":0},"$loki":61},{"_id":"5c3d65bd3525a329e0c0ff17","address":"1166 Sage Dr","location":{"type":"Point","coordinates":[-113.083063624799,37.656828864053]},"isApproved":true,"items":[],"keys":["Mexican"],"lastUpdated":1547527612609,"name":"Brody’s Mexican Restaurant","phone":"(435) 531-8773","price":"$$","reviewCount":85,"reviewScore":4,"meta":{"revision":0,"created":1547531155335,"version":0},"$loki":62},{"_id":"5c3d65bd3525a329e0c14d1a","address":"223 Hunter Ridge Rd","location":{"type":"Point","coordinates":[-113.0828759,37.6567314]},"isApproved":true,"items":[],"keys":["American (New)"],"lastUpdated":1547527612729,"name":"Cedar Breaks Bar & Grill","phone":"(435) 677-3000","price":"$$","reviewCount":45,"reviewScore":3,"meta":{"revision":0,"created":1547531155335,"version":0},"$loki":63},{"_id":"5c3d65bd3525a329e0c112d3","address":"197 W 200th S","location":{"type":"Point","coordinates":[-113.0759298,37.6577818]},"isApproved":true,"items":[],"keys":["Burgers","Steakhouses"],"lastUpdated":1547527612642,"name":"Hamburger Patty’s","phone":"(435) 477-8257","price":"$","reviewCount":45,"reviewScore":4.5,"meta":{"revision":0,"created":1547531155335,"version":0},"$loki":64},{"_id":"5c3d65bd3525a329e0c0eb1a","address":"1760 N Main St","location":{"type":"Point","coordinates":[-113.082682324967,37.6571543137563]},"isApproved":true,"items":[],"keys":["Hawaiian"],"lastUpdated":1547527612581,"name":"Honolulu Grill","phone":"(435) 867-6428","price":"$$","reviewCount":32,"reviewScore":4,"meta":{"revision":0,"created":1547531155335,"version":0},"$loki":65},{"_id":"5c3d65bd3525a329e0c10c34","address":"241 N Main St","location":{"type":"Point","coordinates":[-113.082682324967,37.6571543137563]},"isApproved":true,"items":[],"keys":["Steakhouses","Seafood","American (Traditional)"],"lastUpdated":1547527612633,"name":"Depot Grill","phone":"(435) 865-7445","price":"$$$","reviewCount":120,"reviewScore":3.5,"meta":{"revision":0,"created":1547531155335,"version":0},"$loki":66},{"_id":"5c3d65bd3525a329e0c19999","address":"1237 Sage Dr","location":{"type":"Point","coordinates":[-113.082108,37.658003]},"isApproved":true,"items":[],"keys":["American (Traditional)","Bars","Tex-Mex"],"lastUpdated":1547527612843,"name":"Chili’s","phone":"(435) 586-9700","price":"$$","reviewCount":42,"reviewScore":3,"meta":{"revision":0,"created":1547531155335,"version":0},"$loki":67},{"_id":"5c3d65bd3525a329e0c141cd","address":"1204 S Main St","location":{"type":"Point","coordinates":[-113.0849104,37.6568289]},"isApproved":true,"items":[],"keys":["American (Traditional)"],"lastUpdated":1547527612713,"name":"Bistro 435","phone":"(435) 867-8877","price":"","reviewCount":4,"reviewScore":3.5,"meta":{"revision":0,"created":1547531155335,"version":0},"$loki":68},{"_id":"5c3d65bd3525a329e0c1ada8","address":"410 W State St","location":{"type":"Point","coordinates":[-113.088353,37.6544279858116]},"isApproved":true,"items":[],"keys":["Pizza","Chicken Wings","Sandwiches"],"lastUpdated":1547527612875,"name":"Domino’s Pizza","phone":"(435) 635-3322","price":"$","reviewCount":10,"reviewScore":3.5,"meta":{"revision":0,"created":1547531155335,"version":0},"$loki":69},{"_id":"5c3d65bd3525a329e0c0e591","address":"565 S Main St","location":{"type":"Point","coordinates":[-113.0869669,37.655966]},"isApproved":true,"items":[],"keys":["Food Trucks","Caterers","Breakfast & Brunch"],"lastUpdated":1547527612573,"name":"Pork Belly’s Eatery & Catering","phone":"(435) 586-5285","price":"$$","reviewCount":69,"reviewScore":4.5,"meta":{"revision":0,"created":1547531155335,"version":0},"$loki":70},{"_id":"5c3d65bd3525a329e0c0c2ce","address":"868 Zion Park Blvd","location":{"type":"Point","coordinates":[-113.0854545,37.6563287]},"isApproved":true,"items":[],"keys":["Pizza","Salad","Beer Gardens"],"lastUpdated":1547527612518,"name":"Zion Pizza & Noodle - Temp. CLOSED","phone":"(435) 772-3815","price":"$$","reviewCount":433,"reviewScore":4,"meta":{"revision":0,"created":1547531155335,"version":0},"$loki":71},{"_id":"5c3d65bd3525a329e0c0e6fb","address":"980 W State St","location":{"type":"Point","coordinates":[-113.085669,37.654514]},"isApproved":true,"items":[],"keys":["Barbeque","American (Traditional)","Sandwiches"],"lastUpdated":1547527612574,"name":"Lonny Boy’s Barbeque","phone":"(435) 215-3011","price":"$$","reviewCount":292,"reviewScore":4,"meta":{"revision":0,"created":1547531155335,"version":0},"$loki":72},{"_id":"5c3d65bd3525a329e0c01d3d","address":"1390 S Providence Center Dr","location":{"type":"Point","coordinates":[-113.0851259,37.654723]},"isApproved":true,"items":[],"keys":["Pizza"],"lastUpdated":1547527612259,"name":"5 Buck Pizza","phone":"(435) 865-9600","price":"$","reviewCount":9,"reviewScore":3,"meta":{"revision":0,"created":1547531155335,"version":0},"$loki":73},{"_id":"5c3d65bd3525a329e0c1b528","address":"1130 North 100","location":{"type":"Point","coordinates":[-113.085446096957,37.6544221461015]},"isApproved":true,"items":[],"keys":["Tex-Mex","Fast Food","Mexican"],"lastUpdated":1547527612886,"name":"Taco Bell","phone":"(435) 477-3311","price":"","reviewCount":8,"reviewScore":3.5,"meta":{"revision":0,"created":1547531155335,"version":0},"$loki":74},{"_id":"5c3d65bd3525a329e0c0fe72","address":"1415 S Providence Center Dr","location":{"type":"Point","coordinates":[-113.085569,37.653667]},"isApproved":true,"items":[],"keys":["Mexican"],"lastUpdated":1547527612609,"name":"Costa Vida Fresh Mexican Grill","phone":"(435) 586-1616","price":"$","reviewCount":37,"reviewScore":3.5,"meta":{"revision":0,"created":1547531155335,"version":0},"$loki":75},{"_id":"5c3d65bd3525a329e0c13319","address":"220 N Fork County Rd","location":{"type":"Point","coordinates":[-113.0846634,37.653664]},"isApproved":true,"items":[],"keys":["American (Traditional)"],"lastUpdated":1547527612689,"name":"Ray’s Restaurant","phone":"","price":"","reviewCount":3,"reviewScore":4,"meta":{"revision":0,"created":1547531155335,"version":0},"$loki":76},{"_id":"5c3d65bd3525a329e0c1920a","address":"","location":{"type":"Point","coordinates":[-113.0855772,37.6530469]},"isApproved":true,"items":[],"keys":["Tex-Mex","Bars"],"lastUpdated":1547527612833,"name":"Chili’s Grill & Bar","phone":"","price":"$$","reviewCount":12,"reviewScore":2.5,"meta":{"revision":0,"created":1547531155335,"version":0},"$loki":77},{"_id":"5c3d65bd3525a329e0c04c39","address":"4475 S State","location":{"type":"Point","coordinates":[-112.983942,37.65284]},"isApproved":true,"items":[],"keys":["American (Traditional)"],"lastUpdated":1547527612337,"name":"Golden Hills Restaurant","phone":"(435) 648-2602","price":"$$","reviewCount":57,"reviewScore":4,"meta":{"revision":0,"created":1547531155335,"version":0},"$loki":78},{"_id":"5c3d65bd3525a329e0c0a27b","address":"771 W Hwy 9","location":{"type":"Point","coordinates":[-112.8465335,37.694146]},"isApproved":true,"items":[],"keys":["Diners"],"lastUpdated":1547527612473,"name":"Cactus Room","phone":"(435) 635-7872","price":"$$","reviewCount":64,"reviewScore":4.5,"meta":{"revision":0,"created":1547531155335,"version":0},"$loki":79},{"_id":"5c3d65bd3525a329e0c028fc","address":"625 W 200th S","location":{"type":"Point","coordinates":[-112.846532,37.694161]},"isApproved":true,"items":[],"keys":["Chinese"],"lastUpdated":1547527612285,"name":"Mountain Bistro","phone":"(435) 263-0059","price":"$$","reviewCount":54,"reviewScore":4.5,"meta":{"revision":0,"created":1547531155335,"version":0},"$loki":80},{"_id":"5c3d65bd3525a329e0c13232","address":"40 N 400th W","location":{"type":"Point","coordinates":[-112.6516104,37.7258126]},"isApproved":true,"items":[],"keys":["American (Traditional)","Breakfast & Brunch"],"lastUpdated":1547527612689,"name":"Renegades Restaurant","phone":"(435) 826-4411","price":"","reviewCount":2,"reviewScore":2.5,"meta":{"revision":0,"created":1547531155335,"version":0},"$loki":81},{"_id":"5c3d65bd3525a329e0c16987","address":"35 Lion Blvd","location":{"type":"Point","coordinates":[-112.6516104,37.7258126]},"isApproved":true,"items":[],"keys":["Grocery","Sandwiches","Bakeries"],"lastUpdated":1547527612772,"name":"Hoodoos General Store & Ice Cream Parlor","phone":"(435) 772-3101","price":"$","reviewCount":26,"reviewScore":3.5,"meta":{"revision":0,"created":1547531155335,"version":0},"$loki":82},{"_id":"5c3d65bd3525a329e0c02a7d","address":"30 E State St","location":{"type":"Point","coordinates":[-112.651391,37.702492]},"isApproved":true,"items":[],"keys":["Sandwiches"],"lastUpdated":1547527612286,"name":"Soup Town Cafe","phone":"(435) 648-2370","price":"$","reviewCount":18,"reviewScore":4,"meta":{"revision":0,"created":1547531155335,"version":0},"$loki":83},{"_id":"5c3d65bd3525a329e0c13961","address":"205 Zion Park Blvd","location":{"type":"Point","coordinates":[-112.651391,37.702492]},"isApproved":true,"items":[],"keys":["Coffee & Tea","Pizza","Juice Bars & Smoothies"],"lastUpdated":1547527612698,"name":"Cafe Soleil","phone":"(435) 772-0505","price":"$","reviewCount":552,"reviewScore":4.5,"meta":{"revision":0,"created":1547531155335,"version":0},"$loki":84},{"_id":"5c3d65bd3525a329e0c1a356","address":"394 S State St","location":{"type":"Point","coordinates":[-112.665674159471,37.5247710403918]},"isApproved":true,"items":[],"keys":["Coffee & Tea","Pizza","Beer Bar"],"lastUpdated":1547527612858,"name":"River Rock Roasting Co","phone":"(435) 635-7625","price":"$","reviewCount":503,"reviewScore":4.5,"meta":{"revision":0,"created":1547531155335,"version":0},"$loki":85},{"_id":"5c3d65bd3525a329e0c13f83","address":"1098 W 200th N","location":{"type":"Point","coordinates":[-112.666798,37.5242999]},"isApproved":true,"items":[],"keys":["Mexican"],"lastUpdated":1547527612707,"name":"Valerie’s Taco Shop","phone":"(435) 586-9788","price":"$","reviewCount":24,"reviewScore":4,"meta":{"revision":0,"created":1547531155335,"version":0},"$loki":86},{"_id":"5c3d65bd3525a329e0c1a74d","address":"453 S Main St","location":{"type":"Point","coordinates":[-112.6673485,37.5237682]},"isApproved":true,"items":[],"keys":["Mexican"],"lastUpdated":1547527612866,"name":"La Casa Don Miguel","phone":"(435) 586-6855","price":"$$","reviewCount":201,"reviewScore":4,"meta":{"revision":0,"created":1547531155335,"version":0},"$loki":87},{"_id":"5c3d65bd3525a329e0c0e871","address":"1744 Royal Hunt Dr","location":{"type":"Point","coordinates":[-112.6502672,37.5160124]},"isApproved":true,"items":[],"keys":["Fast Food","Italian"],"lastUpdated":1547527612575,"name":"Bruno’s","phone":"(435) 867-4477","price":"$$","reviewCount":54,"reviewScore":4,"meta":{"revision":0,"created":1547531155335,"version":0},"$loki":88},{"_id":"5c3d65bd3525a329e0c0f14e","address":"1460 E Duck Creek Ridge Rd","location":{"type":"Point","coordinates":[-112.6502672,37.5160124]},"isApproved":true,"items":[],"keys":["Burgers","American (Traditional)","Pizza"],"lastUpdated":1547527612591,"name":"Pinewoods Resort Restaurant","phone":"(435) 682-3660","price":"$$","reviewCount":19,"reviewScore":4,"meta":{"revision":0,"created":1547531155335,"version":0},"$loki":89},{"_id":"5c3d65bd3525a329e0c16ec5","address":"1555 W Regency Rd","location":{"type":"Point","coordinates":[-112.6701237,37.5249576]},"isApproved":true,"items":[],"keys":["American (Traditional)","Chicken Wings","Sports Bars"],"lastUpdated":1547527612781,"name":"Winger’s","phone":"(435) 867-1700","price":"$$","reviewCount":64,"reviewScore":3,"meta":{"revision":0,"created":1547531155335,"version":0},"$loki":90},{"_id":"5c3d65bd3525a329e0c14238","address":"2400 Zion Park Blvd","location":{"type":"Point","coordinates":[-112.955907,37.251696]},"isApproved":true,"items":[],"keys":["Steakhouses"],"lastUpdated":1547527612713,"name":"Arkansas Al’s","phone":"(435) 772-7609","price":"$$$","reviewCount":21,"reviewScore":3,"meta":{"revision":0,"created":1547531155335,"version":0},"$loki":91},{"_id":"5c3d65bd3525a329e0c15c82","address":"575 S 200th E","location":{"type":"Point","coordinates":[-112.875869013369,37.2709437807323]},"isApproved":true,"items":[],"keys":["American (New)","Modern European"],"lastUpdated":1547527612754,"name":"Aragosta","phone":"(435) 313-0611","price":"$$$","reviewCount":98,"reviewScore":5,"meta":{"revision":0,"created":1547531155335,"version":0},"$loki":92},{"_id":"5c3d65bd3525a329e0c0a402","address":"932 Zion Park Blvd","location":{"type":"Point","coordinates":[-112.628448,37.277489]},"isApproved":true,"items":[],"keys":["Coffee & Tea","Juice Bars & Smoothies","Breakfast & Brunch"],"lastUpdated":1547527612480,"name":"Deep Creek Coffee Company","phone":"(435) 669-8849","price":"$","reviewCount":315,"reviewScore":4.5,"meta":{"revision":0,"created":1547531155335,"version":0},"$loki":93},{"_id":"5c3d65bd3525a329e0c127bd","address":"198 Zion Park Blvd","location":{"type":"Point","coordinates":[-112.636495854659,37.2761612157458]},"isApproved":true,"items":[],"keys":["Vietnamese","Thai"],"lastUpdated":1547527612672,"name":"Thai Sapa","phone":"(435) 772-0510","price":"$$","reviewCount":430,"reviewScore":3,"meta":{"revision":0,"created":1547531155335,"version":0},"$loki":94},{"_id":"5c3d65bd3525a329e0c1ac37","address":"1152 Hwy 12","location":{"type":"Point","coordinates":[-112.636495854659,37.2761612157458]},"isApproved":true,"items":[],"keys":["Steakhouses"],"lastUpdated":1547527612869,"name":"UpTop Steakhouse","phone":"(435) 834-5227","price":"","reviewCount":18,"reviewScore":3,"meta":{"revision":0,"created":1547531155335,"version":0},"$loki":95},{"_id":"5c3d65bd3525a329e0c05a7b","address":"545 N Main St","location":{"type":"Point","coordinates":[-112.63812,37.275794]},"isApproved":true,"items":[],"keys":["Cafes"],"lastUpdated":1547527612356,"name":"Cafe Y","phone":"(435) 275-4212","price":"","reviewCount":6,"reviewScore":4,"meta":{"revision":0,"created":1547531155335,"version":0},"$loki":96},{"_id":"5c3d65bd3525a329e0c19858","address":"198 S 100th E","location":{"type":"Point","coordinates":[-112.63812,37.275794]},"isApproved":true,"items":[],"keys":["American (New)","Comfort Food"],"lastUpdated":1547527612842,"name":"Wild Thyme Cafe","phone":"(435) 644-2848","price":"$$","reviewCount":82,"reviewScore":4.5,"meta":{"revision":0,"created":1547531155335,"version":0},"$loki":97},{"_id":"5c3d65bd3525a329e0c08973","address":"314 Hunter Ridge Dr","location":{"type":"Point","coordinates":[-112.802118654351,37.2475125967658]},"isApproved":true,"items":[],"keys":["Steakhouses"],"lastUpdated":1547527612429,"name":"Leany’s Steakhouse","phone":"(435) 677-9000","price":"$$","reviewCount":27,"reviewScore":2.5,"meta":{"revision":0,"created":1547531155335,"version":0},"$loki":98},{"_id":"5c3d65bd3525a329e0c16156","address":"736 Zion Park Blvd","location":{"type":"Point","coordinates":[-112.680623634543,37.2233812113718]},"isApproved":true,"items":[],"keys":["American (Traditional)","Diners","Breakfast & Brunch"],"lastUpdated":1547527612763,"name":"Blondie’s Diner","phone":"(435) 772-0595","price":"$$","reviewCount":162,"reviewScore":3.5,"meta":{"revision":0,"created":1547531155335,"version":0},"$loki":99},{"_id":"5c3d65bd3525a329e0c12bca","address":"70 East 200 North","location":{"type":"Point","coordinates":[-112.681347761059,37.2235877955591]},"isApproved":true,"items":[],"keys":["Pizza"],"lastUpdated":1547527612680,"name":"Papa Murphy’s","phone":"(435) 586-7100","price":"$$","reviewCount":3,"reviewScore":2,"meta":{"revision":0,"created":1547531155335,"version":0},"$loki":100},{"_id":"5c3d65bd3525a329e0c19c15","address":"2107 N Main St","location":{"type":"Point","coordinates":[-112.681594575533,37.2232317493874]},"isApproved":true,"items":[],"keys":["Seafood","Steakhouses"],"lastUpdated":1547527612850,"name":"Lighthouse Seafood and Grill","phone":"(435) 233-2330","price":"$$","reviewCount":48,"reviewScore":4,"meta":{"revision":0,"created":1547531155335,"version":0},"$loki":101},{"_id":"5c3d65bd3525a329e0c0aedf","address":"80 W Center St","location":{"type":"Point","coordinates":[-112.681086994708,37.2237411054568]},"isApproved":true,"items":[],"keys":["Pizza"],"lastUpdated":1547527612491,"name":"5 Buck Pizza","phone":"(435) 865-9600","price":"","reviewCount":1,"reviewScore":1,"meta":{"revision":0,"created":1547531155335,"version":0},"$loki":102},{"_id":"5c3d65bd3525a329e0c094b3","address":"18 E Center St","location":{"type":"Point","coordinates":[-112.5971542,37.3177609]},"isApproved":true,"items":[],"keys":["Asian Fusion","Japanese Curry","Noodles"],"lastUpdated":1547527612453,"name":"Fusion House","phone":"(435) 644-8868","price":"$$","reviewCount":77,"reviewScore":3.5,"meta":{"revision":0,"created":1547531155335,"version":0},"$loki":103},{"_id":"5c3d65bd3525a329e0c10ad1","address":"12 N Main St","location":{"type":"Point","coordinates":[-112.5971542,37.3177609]},"isApproved":true,"items":[],"keys":["Pizza","Salad","Pasta Shops"],"lastUpdated":1547527612631,"name":"Slice Of Veyo","phone":"(435) 218-7291","price":"$","reviewCount":15,"reviewScore":4,"meta":{"revision":0,"created":1547531155335,"version":0},"$loki":104},{"_id":"5c3d65bd3525a329e0c035fc","address":"425 W Main St","location":{"type":"Point","coordinates":[-112.4367641,37.6411869]},"isApproved":true,"items":[],"keys":["Pubs","Tacos","Pool Halls"],"lastUpdated":1547527612303,"name":"4th West Pub","phone":"(435) 826-4525","price":"$$","reviewCount":19,"reviewScore":5,"meta":{"revision":0,"created":1547531155335,"version":0},"$loki":105},{"_id":"5c3d65bd3525a329e0c09547","address":"177 S Main St","location":{"type":"Point","coordinates":[-112.434365,37.64679]},"isApproved":true,"items":[],"keys":["Barbeque","Steakhouses","Pizza"],"lastUpdated":1547527612453,"name":"Hatch Station’s Dining Car Restaurant","phone":"(435) 735-4015","price":"$$","reviewCount":47,"reviewScore":4,"meta":{"revision":0,"created":1547531155335,"version":0},"$loki":106},{"_id":"5c3d65bd3525a329e0c04249","address":"177 S Main St US Hwy 89","location":{"type":"Point","coordinates":[-112.434224280827,37.646720822478]},"isApproved":true,"items":[],"keys":["Southern"],"lastUpdated":1547527612321,"name":"Mountain Harvest","phone":"(435) 735-4014","price":"","reviewCount":3,"reviewScore":4.5,"meta":{"revision":0,"created":1547531155335,"version":0},"$loki":107},{"_id":"5c3d65bd3525a329e0c18915","address":"138 N Main St","location":{"type":"Point","coordinates":[-112.434645045615,37.6471163034337]},"isApproved":true,"items":[],"keys":["Steakhouses","Breweries","Beer, Wine & Spirits"],"lastUpdated":1547527612822,"name":"The Outlaw Saloon","phone":"(435) 233-7201","price":"$$","reviewCount":20,"reviewScore":4,"meta":{"revision":0,"created":1547531155335,"version":0},"$loki":108},{"_id":"5c3d65bd3525a329e0c1aa3d","address":"216 N Main St","location":{"type":"Point","coordinates":[-112.4342067,37.65362]},"isApproved":true,"items":[],"keys":["Diners","American (Traditional)","Breakfast & Brunch"],"lastUpdated":1547527612868,"name":"Galaxy Diner","phone":"(435) 735-4017","price":"$","reviewCount":135,"reviewScore":4,"meta":{"revision":0,"created":1547531155335,"version":0},"$loki":109}],"idIndex":[1,2,3,4,5,6,7,8,9,10,11,12,13,14,15,16,17,18,19,20,21,22,23,24,25,26,27,28,29,30,31,32,33,34,35,36,37,38,39,40,41,42,43,44,45,46,47,48,49,50,51,52,53,54,55,56,57,58,59,60,61,62,63,64,65,66,67,68,69,70,71,72,73,74,75,76,77,78,79,80,81,82,83,84,85,86,87,88,89,90,91,92,93,94,95,96,97,98,99,100,101,102,103,104,105,106,107,108,109],"binaryIndices":{},"constraints":null,"uniqueNames":[],"transforms":{},"objType":"restaurants","dirty":true,"cachedIndex":null,"cachedBinaryIndex":null,"cachedData":null,"adaptiveBinaryIndices":true,"transactional":false,"cloneObjects":false,"cloneMethod":"parse-stringify","asyncListeners":false,"disableMeta":false,"disableChangesApi":true,"disableDeltaChangesApi":true,"autoupdate":false,"serializableIndices":true,"ttl":null,"maxId":109,"DynamicViews":[],"events":{"insert":[],"update":[],"pre-insert":[],"pre-update":[],"close":[],"flushbuffer":[],"error":[],"delete":[null],"warning":[null]},"changes":[]}],"databaseVersion":1.5,"engineVersion":1.5,"autosave":false,"autosaveInterval":5000,"autosaveHandle":null,"throttledSaves":true,"options":{"serializationMethod":"normal","destructureDelimiter":"$<\n"},"persistenceMethod":"fs","persistenceAdapter":null,"verbose":false,"events":{"init":[null],"loaded":[],"flushChanges":[],"close":[],"changes":[],"warning":[]},"ENV":"NODEJS"}