{"filename":"-96.25-38.5","collections":[{"name":"restaurants","data":[{"_id":"5c3d65bd3525a329e0c02c1a","address":"8 E Hwy 99","location":{"type":"Point","coordinates":[-96.165362,38.260263]},"isApproved":true,"items":[],"keys":["Chicken Shop"],"lastUpdated":1547527612287,"name":"Chicken House","phone":"(620) 475-3386","price":"$","reviewCount":12,"reviewScore":4.5,"meta":{"revision":0,"created":1547531151159,"version":0},"$loki":1}],"idIndex":[1],"binaryIndices":{},"constraints":null,"uniqueNames":[],"transforms":{},"objType":"restaurants","dirty":true,"cachedIndex":null,"cachedBinaryIndex":null,"cachedData":null,"adaptiveBinaryIndices":true,"transactional":false,"cloneObjects":false,"cloneMethod":"parse-stringify","asyncListeners":false,"disableMeta":false,"disableChangesApi":true,"disableDeltaChangesApi":true,"autoupdate":false,"serializableIndices":true,"ttl":null,"maxId":1,"DynamicViews":[],"events":{"insert":[],"update":[],"pre-insert":[],"pre-update":[],"close":[],"flushbuffer":[],"error":[],"delete":[null],"warning":[null]},"changes":[]}],"databaseVersion":1.5,"engineVersion":1.5,"autosave":false,"autosaveInterval":5000,"autosaveHandle":null,"throttledSaves":true,"options":{"serializationMethod":"normal","destructureDelimiter":"$<\n"},"persistenceMethod":"fs","persistenceAdapter":null,"verbose":false,"events":{"init":[null],"loaded":[],"flushChanges":[],"close":[],"changes":[],"warning":[]},"ENV":"NODEJS"}